setup.py
bin/grass
grass/__init__.py
grass/iterGrass.py
grass/processLabels.py
grass.egg-info/PKG-INFO
grass.egg-info/SOURCES.txt
grass.egg-info/dependency_links.txt
grass.egg-info/not-zip-safe
grass.egg-info/requires.txt
grass.egg-info/top_level.txt