Metadata-Version: 1.0
Name: grass
Version: 0.1.1
Summary: Annotation of de novo assemblies using semi-supervised learning on graphs
Home-page: https://github.com/COMBINE-lab/GRASS
Author: Laraib Malik, Shravya Thatipally, Nikhil Junneti, Rob Patro
Author-email: rob.patro@cs.stonybrook.edu
License: BSD with attribution
Platform: UNKNOWN
